Metadata-Version: 2.1
Name: CMDpy
Version: 0.4
Summary: A package for work with console.
Home-page: 
